cdpi/__init__.py
cdpi/_pattern.py
cdpi/causal_discovery/__init__.py
cdpi/causal_discovery/util.py
cdpi/causal_discovery/constraint_based_algorithm/__init__.py
cdpi/causal_discovery/constraint_based_algorithm/_basic.py
cdpi/causal_discovery/constraint_based_algorithm/_cpc.py
cdpi/causal_discovery/constraint_based_algorithm/_pc.py
cdpi/causal_discovery/test/__init__.py
cdpi/causal_discovery/test/_conditional_mutual_information_test.py
cdpi/causal_discovery/test/_kcit.py
cdpi-0.1.1.dist-info/LICENSE
cdpi-0.1.1.dist-info/METADATA
cdpi-0.1.1.dist-info/WHEEL
cdpi-0.1.1.dist-info/top_level.txt
cdpi-0.1.1.dist-info/RECORD
