Metadata-Version: 2.1
Name: cdpi
Version: 0.1.1
Summary: Python Implementation of Causal Discovery
Home-page: https://github.com/Ho-Jun-Moon/picd
Author: Technology_Robster
Author-email: metube0113@gmail.com
Classifier: Programming Language :: Python :: 3
Classifier: License :: OSI Approved :: MIT License
Classifier: Operating System :: OS Independent
Requires-Python: >=3.6
License-File: LICENSE
Requires-Dist: numpy
Requires-Dist: scipy
Requires-Dist: pandas
Requires-Dist: matplotlib
